{
  "welcome": "Welcome!",
  "welcome1": "Welcome to WINGI",

  "congratsMsg": "Your shop has been created successfully",
  "signUpMobile": "Sign up using your mobile number",
  "plzEnterMobile": "Please enter your mobile number for one-time password (OTP) verification",
  "enterPhone": "Enter your mobile number",
  "sendOTPMsg": "We will send you an OTP\non this number",
  "requestOTP": "Request OTP",
  "agreeMsg": "I agree to the ",
  "termsOfUse": "Terms of use ",
  "privacyPolicy": "Privacy policy",
  "verifyWithOTP": "Verify with OTP",
  "adding": "Updating cart",
  "addCustomer": "Add customer",
  "myContacts": "My contacts",

  "plzEnterOTP": "Please enter the OTP sent to",
  "resendCode": "Resend Code",
  "verify": "Verify OTP",
  "karibu": "Karibu",
  "buildShop": "Create your shop on WINGI",
  "yourShopName": "Your shop name",
  "havePhysicalShop": "Do you have a physical shop?",
  "descShopDetails": "Describe your shop in one sentence",
  "shopDetails": "Shop details",
  "yourShopAdd": "Your shop address",
  "enterShopAdd": "Enter shop address",
  "proceed": "Proceed",
  "enterPersonalDetails": "Enter your personal details",
  "bring": "Bring your shop online and sell with ease.",
  "firstName": "First name",
  "enterFirstName": "Enter first name",
  "lastName": "Last name",
  "enterlastName": "Enter last name",
  "email": "Email",
  "yourEmail": "Your Email",
  "createShop": "Create shop",
  "selectGender": "Select Gender",
  "gender": "Gender",
  "dob": "Date Of Birth",
  "selectDob": "Select date of birth",
  "invalidEmail": "Invalid email",
  "backtohome": "Back to Home",
  "addAddress": "Add New Address",
  "updateAddress": "Update Address",

  "submit": "Submit",
  "cancel": "Cancel",
  "addProduct": "Add Product",
  "updateProduct": "Update Product",
  "imgGrantPermission": "Please grant storage permission to upload photo.",
  "cameraGrantPermission": "Please grant camera permission to upload photo.",
  "uploadProductImages": "Upload Product Images",
  "prodName": "Product Name",
  "enterProdName": "Enter product name",
  "selectProdCat": "Select product category",
  "prodCat": "Product Category",
  "enterUnitCost": "Enter unit cost",
  "unitCost": "Unit Cost",
  "productUnitCost": "Product Unit Cost",
  "enterUnitSP": "Enter unit selling price",
  "unitSP": "Unit Selling Price",
  "productUnitSP": "Product unit selling price",
  "enterQuantity": "Enter units that you have in stock",
  "quantity": "How many units do you have in stock?",
  "enterProdDescr": "Enter product description",
  "prodDescr": "Product Description",
  "markAsDefault": "Mark as the default product",
  "noProductText": "Your shop is empty. Upload your first product.",
  "noProductDesc": "It taken only few seconds to add your products and start selling to the customers.",
  "alreadyHaveProd": "I already have products",
  "addProd": "Add Product",
  "sourceNewProd": "I want to source new products",
  "viewCatlog": "View WINGI Catalogue",
  "prodTitle": "Products",
  "OrderDraft": "Order Draft",
  "shopName": "Shop Name",
  "myProducts": "My Products",
  "shareProduct": "Share Product",
  "prodInventory": "Product Inventory",
  "searchBarText": "What you wish to sell...",
  "productDraft": "Your order draft is empty.",
  "shareProd": "Share Product",
  "backToProd": "Back to Products",
  "addVariant": "Add Variant",
  "updateVariant": "Update Variant",
  "variantName": "Variant Name",
  "enterVariant": "Enter variant name",
  "aboutProduct": "About Product",
  "prodDetails": "Product Details",
  "style": "Style",
  "articleNo": "Article no.",
  "readMore": "Read more",
  "readLess": "Read less",
  "availableVariants": "Available Variants",
  "sellingPrice": "Selling Price",
  "sortBy": "SORT BY",
  "sortBySmall": "Sort By",

  "totalPrice": "Total Price",
  "viewLess": "View less",
  "viewMore": "View more",
  "createOrder": "Generate Order Sheet",
  "grandTotal": "Grand Total",
  "totalSell": "Total Sell",
  "payDetail": "Payment Details",
  "downPay": "Down Payment",
  "balancePay": "Balance to Pay",
  "earningItem": "Earning on this item ",
  "backtoOrderDetail": "Back to Order Details",
  "enterMob": "Enter phone (used on WhatsApp)",
  "enterName": "Enter name",
  "customerForm": "Customer Form",
  "selectDelivery": "Select Delivery Method",
  "delAddress": "Enter your delivery address",
  "specialReq": "Note: Special Request",
  "genOrderSheet": "Generate Order Sheet",
  "deleteConfirm": "Are you sure you want to delete",
  "delete": "Delete",
  "yes": "YES",
  "no": "NO",
  "orderSheet": "Order Sheet",
  "totalQty": "Total Quantity",
  "deliveryAdd": "Delivery Address",
  "delType": "Delivery Type",
  "shareOrder": "Share Order Sheet",
  "sourcedOrders": "Sourced Orders",
  "sellOrders": "Sell Orders",
  "afterSell": "After Sell",
  "inventory": "Inventory",

  "customers": "Customers",
  "analytics": "Analytics",
  "yourProfilePic": "Your\n profile pic",
  "addProdTooltipMsg": "Add your first product from here",
  "whatsAppTooltipMsg": "Need help?\nConnect with us on WhatsApp",
  "prodCardTooltipMsg": "Click here to manage your product",
  "removeProduct": "Delete this product",
  "removeVariant": "Delete this variant",
  "all": "All",
  "unPaid": "UnPaid",
  "unDelivered": "unDelivered",
  "maxUploadPhotosMsg": "You can only upload maximum 10 photos.",
  "maxUploadPhotosSizeMsg": "Image size should not exceed 2 MB. Ignoring ",
  "selectPayStatus": "Select Payment Type",
  "markAsDefaultVariant": "Mark this as default product instead",
  "productImg": "Product Images",
  "variants": "Variants",
  "sell": "Sell",
  "addOrderDraft": "Add to Order Draft",
  "shareProdInfo": "Product description will get copied. Please paste the description as per your need.",
  "copyProdDescrMsg": "Product description copied successfully.",
  "copyOrderSheetMsg": "Order sheet copied successfully.",
  "sharingImg": "Sharing Images",
  "enter": "Enter an address",

  "updateOrderDraft": "Update Order Draft",
  "deleteOrderDraft": "Delete from Order Draft",
  "unitsToSell": "Enter units to sell",
  "units": "Units",
  "warning": "Warning!",
  "internetOff": "Please make sure you are connected to internet and try again.",
  "continue": "Continue",
  "pickupAddress": "Enter a pick up address",
  "orderAndPay": "Order & Payment Details",
  "enterSellingPrice": "Enter selling price",
  "productName": "Product Name",
  "phoneNo": "Phone Number",
  "name": "Name",
  "deliveryMethod": "Delivery Method",
  "pickupAdd": "Pickup Address",
  "congratulations": "Congratulations!",
  "sellOrderEmpty": "Your sell order is empty",
  "searchByOrder": "Search order...",
  "orderNo": "Order No : ",
  "sourcedDetail": "Sourced Order Sheet",
  "sellOrderSheet": "Sell Order Sheet",
  "custSearchLabel": "Search by name and phone...",
  "sourceSearchLabel": "Search products here...",
  "trendTitle": "Trending on Wingi",
  "checkNow": "Check Now",
  "checkout": "Checkout",
  "updateShop": "Update Shop Details",
  "updateYourShop": "Update your shop details",
  "updateProfile": "Update Profile Details",
  "saveDetails": "Save Details",

  "popularPick": "Popular Picks",
  "bestSellTitle": "Best Sellers",
  "prodForU": "Products for you",
  "unitPrice": "Unit Price",
  "location": "Location",
  "selectLocation": "Select location",
  "myCart": "My Cart",
  "virtualListHeader": "Sell Now, Buy Later",
  "orderTimeText": "Order in the next",
  "addToCart": "Add to Cart",
  "selectVariant": "Select Variant",
  "addToMyCart": "Add to Cart",
  "buyNow": "Buy Now",
  "wish": "Add to Sell Now, Buy Later",

  "addToMyOrder": "Add to my order",
  "selectOrderType": "Order Type",
  "deliveryOptions": "Delivery Options",
  "selectDeliveryOptions": "Select Delivery Option",
  "pickUpLocation": "Pick up location ",
  "enterYourName": "Enter your name",
  "selectCountry": "Select Country",
  "country": "Country",
  "city": "City",

  "paymentPlans": "Payment Plans",
  "payment": "Payment",
  "paymentOptions": "Payment Options",
  "payOptionMsg": "Please share a bit more about your shop for us to evaluate your eligibility for installment payments",
  "wingPayMsg": "Build WINGI credits when you source above 50,000 KSh",
  "suggestedForYou": "Suggested for you",
  "orderedProductTitle": "Products in my Cart",
  "availableNow": "Available Now",
  "interShipping": "International Shipping",
  "expShippingtime": "Expected shipping time",
  "businessDay": "business days",
  "retailersForm": "Retailer's Form",
  "yourFullName": "Your full Name",
  "yourPhone": "Your phone (Use WhatsApp)",
  "yourDob": "Your date of birth",
  "yourGender": "Your gender",
  "enterStoreName": "Enter store name",
  "webSiteLink": "Your website or social media page link",
  "QuestKindOfStore": "What kind of store do you have?",
  "QuestProductTypes": "What products does your store sell?",
  "selectPayPlan": "Select a Payment Plan",
  "selectPayMethod": "Select a Payment Method",
  "paymentMethods": "Payment Methods",
  "totalProduct": "Total Products",
  "placeOrder": "Place Order",
  "sendPrompt": "SEND PROMPT",
  "sendPrompt2": "Send Payment Request",
  "backToHome": "Back to Home",
  "paymentHistory": "Payment History",
  "paymentSearch": "Search by transaction id..",
  "track": "Track My Order",

  "id": "Id: ",
  "selectStoreType": "Select Store Type",
  "SearchCategoryTitle": "Search products",
  "filterBy": "Filter By",
  "enterCountry": "Enter country",
  "enterCity": "Enter city",

  "addAProd": "Add a product",
  "addProdSubTitle": "Add product to your online shop",
  "addExistProd": "Add your existing products",
  "sourceNewProdFromCatlog": "Source new products from WINGI",
  "enterShopName": "Enter your shop name",
  "enterYourEmail": "Enter your email",
  "addToInventory": "Add to Inventory",
  "addInventorySubTitle": "Please enter Selling Price for below products present in your order",
  "makePayment": "Make Payment",
  "imageError": "Invalid image type (Please select only JPEG, PNG & JPG images)",
  "wish": "Add to Wishlist",
  "addToSellNow": "Add to Sell Now,\nBuy Later",
  "checkout": "Checkout",
  "descMandat": "Description is mandatory, if only varients are selected. ",
  "addProductText": "Your shop is empty. Upload your first product by clicking on add button above.",
  "subCategory": "Sub Category",
  "enterSubCategory": "Enter sub category",
  "addInventoryAlertTitle": "Add products to inventory",
  "addInventoryAlertSubtitle": "Have you received the products? Add them to your inventory to start selling.",
  "otherCategory": "Enter other category",
  "orderStatusAlertSubTitle": "Are you sure, you want to"
}
